mihome/__init__.py
mihome/connector.py
mihome-0.1.dist-info/DESCRIPTION.rst
mihome-0.1.dist-info/METADATA
mihome-0.1.dist-info/RECORD
mihome-0.1.dist-info/WHEEL
mihome-0.1.dist-info/entry_points.txt
mihome-0.1.dist-info/metadata.json
mihome-0.1.dist-info/top_level.txt
