Metadata-Version: 2.0
Name: mihome
Version: 0.1
Summary: Xiaomi Mi Home Python bindings
Home-page: https://github.com/jon1012/mihome
Author: Jonathan Schemoul
Author-email: jonathan.schemoul@gmail.com
License: MIT
Keywords: xiaomi udp paquet iot mi home aqara
Platform: UNKNOWN
Classifier: Development Status :: 4 - Beta
Classifier: License :: OSI Approved :: MIT License
Classifier: Programming Language :: Python :: 2
Classifier: Programming Language :: Python :: 3
Classifier: Intended Audience :: Developers
Classifier: Intended Audience :: System Administrators
Classifier: Topic :: System :: Hardware
Requires-Dist: future
